kisumu/__init__.py
kisumu-0.2.0.dist-info/LICENSE.txt
kisumu-0.2.0.dist-info/METADATA
kisumu-0.2.0.dist-info/WHEEL
kisumu-0.2.0.dist-info/entry_points.txt
kisumu-0.2.0.dist-info/RECORD
