Metadata-Version: 2.3
Name: kisumu
Version: 0.2.0
Summary: A command line interface for jinja-rdf
License: EUPL-1.2
Author: Natanael Arndt
Author-email: arndtn@gmail.com
Requires-Python: >=3.11,<4.0
Classifier: License :: OSI Approved :: European Union Public Licence 1.2 (EUPL 1.2)
Classifier: Programming Language :: Python :: 3
Classifier: Programming Language :: Python :: 3.11
Classifier: Programming Language :: Python :: 3.12
Classifier: Programming Language :: Python :: 3.13
Requires-Dist: click (>=8.1.8,<9.0.0)
Requires-Dist: jinja-rdf (>=0.1.0,<0.2.0)
Requires-Dist: loguru (>=0.7.2,<0.8.0)
Requires-Dist: rdflib (>=7.1.1,<8.0.0)
Project-URL: Repository, https://github.com/aksw/kisumu
